tbn/__init__.py
tbn/network.py
torch_base_network-0.0.2.dist-info/METADATA
torch_base_network-0.0.2.dist-info/WHEEL
torch_base_network-0.0.2.dist-info/top_level.txt
torch_base_network-0.0.2.dist-info/RECORD
